embedbase_internet_search/__init__.py
embedbase_internet_search/bing.py
embedbase_internet_search/endpoint.py
embedbase_internet_search-1.0.0.dist-info/LICENSE
embedbase_internet_search-1.0.0.dist-info/METADATA
embedbase_internet_search-1.0.0.dist-info/WHEEL
embedbase_internet_search-1.0.0.dist-info/RECORD
