Metadata-Version: 2.1
Name: embedbase-internet-search
Version: 1.0.0
Summary: An internet search extension for Embedbase
Home-page: https://github.com/different-ai/embedbase-internet-search
License: MIT
Keywords: embeddings,machine learning,artificial intelligence,llm
Author: Different AI
Author-email: louis@embedbase.xyz
Requires-Python: >=3.8,<4.0
Classifier: Development Status :: 4 - Beta
Classifier: Intended Audience :: Developers
Classifier: License :: OSI Approved :: MIT License
Classifier: Programming Language :: Python :: 3
Classifier: Programming Language :: Python :: 3.8
Classifier: Programming Language :: Python :: 3.9
Classifier: Programming Language :: Python :: 3.10
Classifier: Programming Language :: Python :: 3.11
Classifier: Programming Language :: Python :: 3
Classifier: Programming Language :: Python :: 3.10
Classifier: Programming Language :: Python :: 3.8
Classifier: Programming Language :: Python :: 3.9
Classifier: Topic :: Scientific/Engineering :: Artificial Intelligence
Requires-Dist: embedbase (>=1.2.1,<2.0.0)
Project-URL: Repository, https://github.com/different-ai/embedbase-internet-search
